kolibri_app_desktop_xdg_plugin/__init__.py
kolibri_app_desktop_xdg_plugin/apps.py
kolibri_app_desktop_xdg_plugin/channel_launchers.py
kolibri_app_desktop_xdg_plugin/kolibri_plugin.py
kolibri_app_desktop_xdg_plugin/path_utils.py
kolibri_app_desktop_xdg_plugin/pillow_utils.py
kolibri_app_desktop_xdg_plugin/management/__init__.py
kolibri_app_desktop_xdg_plugin/management/commands/__init__.py
kolibri_app_desktop_xdg_plugin/management/commands/app_desktop_xdg_update_launchers.py
kolibri_app_desktop_xdg_plugin-1.3.0.dist-info/LICENSE
kolibri_app_desktop_xdg_plugin-1.3.0.dist-info/METADATA
kolibri_app_desktop_xdg_plugin-1.3.0.dist-info/WHEEL
kolibri_app_desktop_xdg_plugin-1.3.0.dist-info/entry_points.txt
kolibri_app_desktop_xdg_plugin-1.3.0.dist-info/top_level.txt
kolibri_app_desktop_xdg_plugin-1.3.0.dist-info/RECORD
