Metadata-Version: 2.1
Name: kolibri-app-desktop-xdg-plugin
Version: 1.3.0
Summary: Kolibri plugin for Linux desktop app integration
Home-page: https://github.com/endlessm/kolibri-app-desktop-xdg-plugin
Author: Dylan McCall
Author-email: dylan@endlessos.org
License: MIT
Keywords: kolibri
Classifier: Development Status :: 2 - Pre-Alpha
Classifier: Intended Audience :: Developers
Classifier: License :: OSI Approved :: MIT License
Classifier: Natural Language :: English
Classifier: Programming Language :: Python :: 3
Classifier: Programming Language :: Python :: 3.6
Classifier: Programming Language :: Python :: 3.7
Classifier: Programming Language :: Python :: 3.8
Classifier: Programming Language :: Python :: 3.9
Classifier: Programming Language :: Python :: Implementation :: PyPy
License-File: LICENSE
Requires-Dist: kolibri >=0.14.6
Requires-Dist: Pillow <11.0.0,>=10.1.0
